[
  {
    "id": "14cfabe5a2984bf3142f3f307757f6b1",
    "source": "github",
    "type": "trending_repository",
    "title": "x1xhlol / system-prompts-and-models-of-ai-tools",
    "description": "",
    "url": "https://github.com/x1xhlol/system-prompts-and-models-of-ai-tools",
    "published_date": "2026-02-17T11:22:32Z",
    "categories": [],
    "metadata": {
      "stars": 126130,
      "forks": 32325,
      "stars_today": 10578,
      "language": "",
      "timeframe": "weekly",
      "repo_path": "x1xhlol/system-prompts-and-models-of-ai-tools"
    }
  },
  {
    "id": "acf98720b428f908fc704200af0875e2",
    "source": "github",
    "type": "trending_repository",
    "title": "obra / superpowers",
    "description": "",
    "url": "https://github.com/obra/superpowers",
    "published_date": "2026-02-21T19:07:39Z",
    "categories": [
      "Shell"
    ],
    "metadata": {
      "stars": 65368,
      "forks": 4981,
      "stars_today": 8563,
      "language": "Shell",
      "timeframe": "weekly",
      "repo_path": "obra/superpowers"
    }
  },
  {
    "id": "3bf706a7aa385c3fe6d3b297a2d22be1",
    "source": "github",
    "type": "trending_repository",
    "title": "huggingface / skills",
    "description": "",
    "url": "https://github.com/huggingface/skills",
    "published_date": "2026-02-27T08:31:22Z",
    "categories": [
      "Python"
    ],
    "metadata": {
      "stars": 7419,
      "forks": 435,
      "stars_today": 5938,
      "language": "Python",
      "timeframe": "weekly",
      "repo_path": "huggingface/skills"
    }
  },
  {
    "id": "1b859793fe74daa9b363bedc93158203",
    "source": "github",
    "type": "trending_repository",
    "title": "vxcontrol / pentagi",
    "description": "",
    "url": "https://github.com/vxcontrol/pentagi",
    "published_date": "2026-02-25T16:26:25Z",
    "categories": [
      "Go"
    ],
    "metadata": {
      "stars": 8607,
      "forks": 960,
      "stars_today": 5598,
      "language": "Go",
      "timeframe": "weekly",
      "repo_path": "vxcontrol/pentagi"
    }
  },
  {
    "id": "0be383045deda3d1895cffb687c6d492",
    "source": "github",
    "type": "trending_repository",
    "title": "muratcankoylan / Agent-Skills-for-Context-Engineering",
    "description": "",
    "url": "https://github.com/muratcankoylan/Agent-Skills-for-Context-Engineering",
    "published_date": "2025-12-24T06:21:00Z",
    "categories": [
      "Python"
    ],
    "metadata": {
      "stars": 12640,
      "forks": 978,
      "stars_today": 3832,
      "language": "Python",
      "timeframe": "weekly",
      "repo_path": "muratcankoylan/Agent-Skills-for-Context-Engineering"
    }
  },
  {
    "id": "4453d299f231fc9bc9040da0f8cb3176",
    "source": "github",
    "type": "trending_repository",
    "title": "clockworklabs / SpacetimeDB",
    "description": "",
    "url": "https://github.com/clockworklabs/SpacetimeDB",
    "published_date": "2026-02-26T19:54:16Z",
    "categories": [
      "Rust"
    ],
    "metadata": {
      "stars": 21481,
      "forks": 780,
      "stars_today": 2036,
      "language": "Rust",
      "timeframe": "weekly",
      "repo_path": "clockworklabs/SpacetimeDB"
    }
  },
  {
    "id": "7b69149178062a40cc96d856fafe0851",
    "source": "github",
    "type": "trending_repository",
    "title": "LadybirdBrowser / ladybird",
    "description": "",
    "url": "https://github.com/LadybirdBrowser/ladybird",
    "published_date": "2026-02-28T06:04:06Z",
    "categories": [
      "C++"
    ],
    "metadata": {
      "stars": 60626,
      "forks": 2803,
      "stars_today": 1922,
      "language": "C++",
      "timeframe": "weekly",
      "repo_path": "LadybirdBrowser/ladybird"
    }
  },
  {
    "id": "739e69c8696afe047511331b677c3d52",
    "source": "github",
    "type": "trending_repository",
    "title": "bytedance / deer-flow",
    "description": "",
    "url": "https://github.com/bytedance/deer-flow",
    "published_date": "2026-02-28T08:20:26Z",
    "categories": [
      "Python"
    ],
    "metadata": {
      "stars": 22330,
      "forks": 2700,
      "stars_today": 1607,
      "language": "Python",
      "timeframe": "weekly",
      "repo_path": "bytedance/deer-flow"
    }
  },
  {
    "id": "55ef787c68ac2760e0f9b10a5d9ca4bf",
    "source": "github",
    "type": "trending_repository",
    "title": "ruvnet / ruvector",
    "description": "",
    "url": "https://github.com/ruvnet/ruvector",
    "published_date": "2026-02-25T16:34:16Z",
    "categories": [
      "Rust"
    ],
    "metadata": {
      "stars": 2030,
      "forks": 205,
      "stars_today": 1407,
      "language": "Rust",
      "timeframe": "weekly",
      "repo_path": "ruvnet/ruvector"
    }
  },
  {
    "id": "7ca8a1da6e065af7911672e6ae7ad37e",
    "source": "github",
    "type": "trending_repository",
    "title": "Stremio / stremio-web",
    "description": "",
    "url": "https://github.com/Stremio/stremio-web",
    "published_date": "2026-01-22T15:44:07Z",
    "categories": [
      "JavaScript"
    ],
    "metadata": {
      "stars": 10276,
      "forks": 1097,
      "stars_today": 1227,
      "language": "JavaScript",
      "timeframe": "weekly",
      "repo_path": "Stremio/stremio-web"
    }
  },
  {
    "id": "1c9eb84826890654985e7b1669cb8b05",
    "source": "github",
    "type": "trending_repository",
    "title": "cloudflare / agents",
    "description": "",
    "url": "https://github.com/cloudflare/agents",
    "published_date": "2026-02-25T09:07:57Z",
    "categories": [
      "TypeScript"
    ],
    "metadata": {
      "stars": 4366,
      "forks": 437,
      "stars_today": 1104,
      "language": "TypeScript",
      "timeframe": "weekly",
      "repo_path": "cloudflare/agents"
    }
  },
  {
    "id": "1b66726332c1e62f20d0ff1536d0479a",
    "source": "github",
    "type": "trending_repository",
    "title": "mihail911 / modern-software-dev-assignments",
    "description": "",
    "url": "https://github.com/mihail911/modern-software-dev-assignments",
    "published_date": "2025-11-10T17:06:44Z",
    "categories": [
      "Python"
    ],
    "metadata": {
      "stars": 2567,
      "forks": 581,
      "stars_today": 651,
      "language": "Python",
      "timeframe": "weekly",
      "repo_path": "mihail911/modern-software-dev-assignments"
    }
  }
]